vpype_dxf/dread.py
vpype_dxf-0.2.0.dist-info/LICENSE
vpype_dxf-0.2.0.dist-info/METADATA
vpype_dxf-0.2.0.dist-info/WHEEL
vpype_dxf-0.2.0.dist-info/entry_points.txt
vpype_dxf-0.2.0.dist-info/top_level.txt
vpype_dxf-0.2.0.dist-info/RECORD
