Metadata-Version: 2.1
Name: vpype-dxf
Version: 0.2.0
Summary: vpype dxf plugin
Home-page: https://github.com/tatarize/vpype-dxf/
Author: Tatarize
Author-email: tatarize@gmail.com
License: UNKNOWN
Platform: UNKNOWN
Classifier: Programming Language :: Python :: 3.6
Classifier: Programming Language :: Python :: 3.7
Classifier: License :: OSI Approved :: MIT License
Classifier: Operating System :: OS Independent
Requires-Dist: click
Requires-Dist: vpype (<2.0,>=1.9)
Requires-Dist: numpy
Requires-Dist: ezdxf (>=0.14.0)
Requires-Dist: svgelements (>=1.4.0)
